[
{"drones": {"image_url": "https://i5.walmartimages.com/asr/598a7c18-86a4-4823-aceb-4f8d04aa777c_1.e05d4a563731eae10cce0b08025cc89c.jpeg?odnHeight=450&odnWidth=450&odnBg=FFFFFF", "shop_name": "WALMART", "shop_link": "https://www.walmart.com/ip/SkyDrones-FX-Mini-Pocket-Drone-Color-may-vary/56123508", "price": "$9", "title": "SkyDrones- FX Mini Pocket Drone (Color may vary)", "searched_keyword": "drones", "content_description": "Skydrones- Fx Mini Pocket Drone", "date_searched": "2019-01-04 00:50:34.386646", "numeric_price": "9"}},
{"drones": {"image_url": "https://i5.walmartimages.com/asr/f688b450-527e-4a20-a150-df06f7bebb17_1.662b204ad6e4f10fc3b36811d57a1f61.jpeg?odnHeight=450&odnWidth=450&odnBg=FFFFFF", "shop_name": "WALMART", "shop_link": "https://www.walmart.com/ip/Sky-Drones-LX-6-LED-Quadcopter/290654456", "price": "$13", "title": "Sky Drones- LX-6 LED Quadcopter", "searched_keyword": "drones", "content_description": "Flying Time 6-8 Minutes Per BatteryCharging Time: 60 minutesControl Distance \u2013 100 Feet", "date_searched": "2019-01-04 00:50:34.855058", "numeric_price": "13"}}
]